[
    {
        "id": 0,
        "text": "Совокупность перспективных способов получения, передачи и использования энергии, которые распространены не так широко, как традиционные, однако представляют интерес из-за выгодности их использования и, как правило, низком риске причинения вреда окружающей среде.",
        "rightAnswer": "Альтернативная энергетика",
        "wrongAnswers": [
            "Ветроэнергетика",
            "Биотопливо",
            "Солнечная энергетика",
            "Гидроэнергетика"
        ]
    },
    {
        "id": 1,
        "text": "Отрасль энергетики, специализирующаяся на преобразовании кинетической энергии воздушных масс в атмосфере в электрическую, механическую, тепловую или в любую другую форму энергии, удобную для использования в народном хозяйстве.",
        "rightAnswer": "Ветроэнергетика",
        "wrongAnswers": [
            "Альтернативная энергетика",
            "Биотопливо",
            "Солнечная энергетика",
            "Гидроэнергетика"
        ]
    },
    {
        "id": 2,
        "text": "Топливо из растительного или животного сырья, из продуктов жизнедеятельности организмов или органических промышленных отходов.",
        "rightAnswer": "Биотопливо",
        "wrongAnswers": [
            "Ветроэнергетика",
            "Альтернативная энергетика",
            "Солнечная энергетика",
            "Гидроэнергетика"
        ]
    },
    {
        "id": 3,
        "text": "Направление альтернативной энергетики, основанное на непосредственном использовании солнечного излучения для получения энергии в каком-либо виде.",
        "rightAnswer": "Солнечная энергетика",
        "wrongAnswers": [
            "Биотопливо",
            "Ветроэнергетика",
            "Альтернативная энергетика",
            "Гидроэнергетика"
        ]
    },
    {
        "id": 4,
        "text": "Область хозяйственно-экономической деятельности человека, совокупность больших естественных и искусственных подсистем, служащих для преобразования энергии водного потока в электрическую энергию.",
        "rightAnswer": "Гидроэнергетика",
        "wrongAnswers": [
            "Солнечная энергетика",
            "Биотопливо",
            "Ветроэнергетика",
            "Альтернативная энергетика"
        ]
    },
    {
        "id": 5,
        "text": "Направление энергетики, основанное на производстве электрической энергии за счёт энергии, содержащейся в недрах земли, на геотермальных станциях.",
        "rightAnswer": "Геотермальная энергетика",
        "wrongAnswers": [
            "Грозовая энергетика",
            "Управляемый термоядерный синтез",
            "Распределённое производство энергии",
            "Водородная энергетика"
        ]
    },
    {
        "id": 6,
        "text": "Способ получения энергии путём поимки и перенаправления энергии молний в электросеть.",
        "rightAnswer": "Грозовая энергетика",
        "wrongAnswers": [
            "Геотермальная энергетика",
            "Управляемый термоядерный синтез",
            "Распределённое производство энергии",
            "Водородная энергетика"
        ]
    },
    {
        "id": 7,
        "text": "Синтез более тяжёлых атомных ядер из более лёгких с целью получения энергии, который носит управляемый характер.",
        "rightAnswer": "Управляемый термоядерный синтез",
        "wrongAnswers": [
            "Геотермальная энергетика",
            "Грозовая энергетика",
            "Распределённое производство энергии",
            "Водородная энергетика"
        ]
    },
    {
        "id": 8,
        "text": "Новая тенденция в энергетике, связанная с производством тепловой и электрической энергии.",
        "rightAnswer": "Распределённое производство энергии",
        "wrongAnswers": [
            "Геотермальная энергетика",
            "Грозовая энергетика",
            "Управляемый термоядерный синтез",
            "Водородная энергетика"
        ]
    },
    {
        "id": 9,
        "text": "Отрасль энергетики, основанное на использовании водорода в качестве средства для аккумулирования, транспортировки и потребления энергии людьми.",
        "rightAnswer": "Водородная энергетика",
        "wrongAnswers": [
            "Геотермальная энергетика",
            "Грозовая энергетика",
            "Управляемый термоядерный синтез",
            "Распределённое производство энергии"
        ]
    },
    {
        "id": 10,
        "text": "Устройство для преобразования кинетической энергии ветрового потока в механическую энергию вращения ротора с последующим ее преобразованием в электрическую энергию.",
        "rightAnswer": "Ветрогенератор",
        "wrongAnswers": [
            "Ветряная электростанция",
            "Наземная ветряная электростанция",
            "Прибрежная ветряная электростанция",
            "Шельфовая ветряная электростанция"
        ]
    },
    {
        "id": 11,
        "text": "Несколько ВЭУ, собранных в одном или нескольких местах и объединённых в единую сеть.",
        "rightAnswer": "Ветряная электростанция",
        "wrongAnswers": [
            "Ветрогенератор",
            "Наземная ветряная электростанция",
            "Прибрежная ветряная электростанция",
            "Шельфовая ветряная электростанция"
        ]
    },
    {
        "id": 12,
        "text": "Тип ветряных электростанций, ветрогенераторы которых устанавливаются на холмах или возвышенностях.",
        "rightAnswer": "Наземная ветряная электростанция",
        "wrongAnswers": [
            "Ветрогенератор",
            "Ветряная электростанция",
            "Прибрежная ветряная электростанция",
            "Шельфовая ветряная электростанция"
        ]
    },
    {
        "id": 13,
        "text": "Тип ветряных электростанций, ветрогенераторы которых устанавливаются на небольшом удалении от берега моря или океана.",
        "rightAnswer": "Прибрежная ветряная электростанция",
        "wrongAnswers": [
            "Ветрогенератор",
            "Ветряная электростанция",
            "Наземная ветряная электростанция",
            "Шельфовая ветряная электростанция"
        ]
    },
    {
        "id": 14,
        "text": "Тип ветряных электростанций, ветрогенераторы которых устанавливаются в море, 10—60 километров от берега.",
        "rightAnswer": "Шельфовая ветряная электростанция",
        "wrongAnswers": [
            "Ветрогенератор",
            "Ветряная электростанция",
            "Наземная ветряная электростанция",
            "Прибрежная ветряная электростанция"
        ]
    },
    {
        "id": 15,
        "text": "Получение электроэнергии с помощью фотоэлементов.",
        "rightAnswer": "Фотовольтаика",
        "wrongAnswers": [
            "Гелиотермальная энергетика",
            "Двигатель Стирлинга",
            "Солнечный коллектор",
            "Солнечный водонагреватель"
        ]
    },
    {
        "id": 16,
        "text": "Нагревание поверхности, поглощающей солнечные лучи, и последующее распределение и использование тепла.",
        "rightAnswer": "Гелиотермальная энергетика",
        "wrongAnswers": [
            "Фотовольтаика",
            "Двигатель Стирлинга",
            "Солнечный коллектор",
            "Солнечный водонагреватель"
        ]
    },
    {
        "id": 17,
        "text": "Тепловая машина, в которой жидкое или газообразное рабочее тело движется в замкнутом объёме, разновидность двигателя внешнего сгорания.",
        "rightAnswer": "Двигатель Стирлинга",
        "wrongAnswers": [
            "Фотовольтаика",
            "Гелиотермальная энергетика",
            "Солнечный коллектор",
            "Солнечный водонагреватель"
        ]
    },
    {
        "id": 18,
        "text": "Устройство для сбора тепловой энергии Солнца (гелиоустановка), переносимой видимым светом и ближним инфракрасным излучением.",
        "rightAnswer": "Солнечный коллектор",
        "wrongAnswers": [
            "Фотовольтаика",
            "Гелиотермальная энергетика",
            "Двигатель Стирлинга",
            "Солнечный водонагреватель"
        ]
    },
    {
        "id": 19,
        "text": "Разновидность солнечного коллектора, предназначен для производства горячей воды путём поглощения солнечного излучения, преобразования его в тепло, аккумуляции и передачи потребителю.",
        "rightAnswer": "Солнечный водонагреватель",
        "wrongAnswers": [
            "Фотовольтаика",
            "Гелиотермальная энергетика",
            "Двигатель Стирлинга",
            "Солнечный коллектор"
        ]
    },
    {
        "id": 20,
        "text": "Полная энергия ветрового потока какой-либо местности на определенной высоте над поверхностью земли.",
        "rightAnswer": "Ветровой потенциал",
        "wrongAnswers": [
            "Валовой потенциал",
            "Технический потенциал",
            "Экономический потенциал",
            "Ветровой кадастр"
        ]
    },
    {
        "id": 21,
        "text": "Энергетический эквивалент ветрового потока какой-либо местности на определенной высоте над поверхностью земли.",
        "rightAnswer": "Валовой потенциал",
        "wrongAnswers": [
            "Ветровой потенциал",
            "Технический потенциал",
            "Экономический потенциал",
            "Ветровой кадастр"
        ]
    },
    {
        "id": 22,
        "text": "Часть валового потенциала, которая может быть полезно использована с помощью современного ветроэнергетического оборудования с учетом требований социально-экологического характера.",
        "rightAnswer": "Технический потенциал",
        "wrongAnswers": [
            "Ветровой потенциал",
            "Валовой потенциал",
            "Экономический потенциал",
            "Ветровой кадастр"
        ]
    },
    {
        "id": 23,
        "text": "Часть технического потенциала, использование которого экономически эффективно в современных условиях с учетом требований социально-экономического характера.",
        "rightAnswer": "Экономический потенциал",
        "wrongAnswers": [
            "Ветровой потенциал",
            "Валовой потенциал",
            "Технический потенциал",
            "Ветровой кадастр"
        ]
    },
    {
        "id": 24,
        "text": "Систематизированный свод сведений, характеризующий ветровые условия местности и дающий возможность количественной оценки энергии ветра и расчета ожидаемой выработки ветроэнергетическими установками.",
        "rightAnswer": "Ветровой кадастр",
        "wrongAnswers": [
            "Ветровой потенциал",
            "Валовой потенциал",
            "Технический потенциал",
            "Экономический потенциал"
        ]
    },
    {
        "id": 25,
        "text": "Электростанция, предназначенная для преобразования энергии солнечного излучения в электрическую энергию.",
        "rightAnswer": "Солнечная электростанция",
        "wrongAnswers": [
            "Солнечно-топливная электростанция",
            "Солнечное теплоснабжение",
            "Солнечное горячее водоснабжение",
            "Солнечное охлаждение"
        ]
    },
    {
        "id": 26,
        "text": "Электростанция, преобразующая по единой технологической схеме энергию солнечного излучения и химическую энергию топлива в электрическую и тепловую энергию.",
        "rightAnswer": "Солнечно-топливная электростанция",
        "wrongAnswers": [
            "Солнечная электростанция",
            "Солнечное теплоснабжение",
            "Солнечное горячее водоснабжение",
            "Солнечное охлаждение"
        ]
    },
    {
        "id": 27,
        "text": "Использование энергии солнечного излучения для отопления, горячего водоснабжения и обеспечения технологических нужд различных потребителей.",
        "rightAnswer": "Солнечное теплоснабжение",
        "wrongAnswers": [
            "Солнечная электростанция",
            "Солнечно-топливная электростанция",
            "Солнечное горячее водоснабжение",
            "Солнечное охлаждение"
        ]
    },
    {
        "id": 28,
        "text": "Использование энергии солнечного излучения для нагрева воды с целью обеспечения коммунально-бытовых и технологических нужд различных потребителей.",
        "rightAnswer": "Солнечное горячее водоснабжение",
        "wrongAnswers": [
            "Солнечная электростанция",
            "Солнечно-топливная электростанция",
            "Солнечное теплоснабжение",
            "Солнечное охлаждение"
        ]
    },
    {
        "id": 29,
        "text": "Использование энергии солнечного излучения для получения холода с целью кондиционирования воздуха, хранения продуктов и т.п.",
        "rightAnswer": "Солнечное охлаждение",
        "wrongAnswers": [
            "Солнечная электростанция",
            "Солнечно-топливная электростанция",
            "Солнечное теплоснабжение",
            "Солнечное горячее водоснабжение"
        ]
    },
    {
        "id": 30,
        "text": "Преобразователь энергии солнечного излучения в электрическую энергию, выполненный на основе различных физических принципов прямого преобразования.",
        "rightAnswer": "Солнечный элемент",
        "wrongAnswers": [
            "Солнечный фотоэлектрический элемент",
            "Двусторонний солнечный элемент",
            "Термоэлектрический солнечный элемент",
            "Термоэлектронный солнечный преобразователь"
        ]
    },
    {
        "id": 31,
        "text": "Солнечный элемент на основе фотоэффекта.",
        "rightAnswer": "Солнечный фотоэлектрический элемент",
        "wrongAnswers": [
            "Солнечный элемент",
            "Двусторонний солнечный элемент",
            "Термоэлектрический солнечный элемент",
            "Термоэлектронный солнечный преобразователь"
        ]
    },
    {
        "id": 32,
        "text": "Солнечный элемент с двусторонней фоточувствительностью.",
        "rightAnswer": "Двусторонний солнечный элемент",
        "wrongAnswers": [
            "Солнечный элемент",
            "Солнечный фотоэлектрический элемент",
            "Термоэлектрический солнечный элемент",
            "Термоэлектронный солнечный преобразователь"
        ]
    },
    {
        "id": 33,
        "text": "Солнечный элемент на основе термоэлектрических явлений, в котором источником тепла является энергия солнечного излучения.",
        "rightAnswer": "Термоэлектрический солнечный элемент",
        "wrongAnswers": [
            "Солнечный элемент",
            "Солнечный фотоэлектрический элемент",
            "Двусторонний солнечный элемент",
            "Термоэлектронный солнечный преобразователь"
        ]
    },
    {
        "id": 34,
        "text": "Солнечный преобразователь на основе явления термоэлектронной эмиссии, в котором источником тепла является энергия солнечного излучения.",
        "rightAnswer": "Термоэлектронный солнечный преобразователь",
        "wrongAnswers": [
            "Солнечный элемент",
            "Солнечный фотоэлектрический элемент",
            "Двусторонний солнечный элемент",
            "Термоэлектрический солнечный элемент"
        ]
    },
    {
        "id": 35,
        "text": "Солнечная электростанция, в которой энергия солнечного излучения используется как источник тепла в термодинамическом цикле преобразования тепловой энергии в механическую, а затем в электрическую.",
        "rightAnswer": "Термодинамическая солнечная электростанция",
        "wrongAnswers": [
            "Фотоэлектрическая солнечная электростанция",
            "Башенная солнечная электростанция",
            "Двухконтурная солнечная электростанция",
            "Модульная солнечная электростанция"
        ]
    },
    {
        "id": 36,
        "text": "Солнечная электростанция, в которой используется способ прямого преобразования энергии солнечного излучения в электрическую энергию.",
        "rightAnswer": "Фотоэлектрическая солнечная электростанция",
        "wrongAnswers": [
            "Термодинамическая солнечная электростанция",
            "Башенная солнечная электростанция",
            "Двухконтурная солнечная электростанция",
            "Модульная солнечная электростанция"
        ]
    },
    {
        "id": 37,
        "text": "Солнечная электростанция, в которой излучение от оптической концентрирующей системы, образованной полем гелиостатов, направляется на установленный на башне приемник энергии солнечного излучения.",
        "rightAnswer": "Башенная солнечная электростанция",
        "wrongAnswers": [
            "Термодинамическая солнечная электростанция",
            "Фотоэлектрическая солнечная электростанция",
            "Двухконтурная солнечная электростанция",
            "Модульная солнечная электростанция"
        ]
    },
    {
        "id": 38,
        "text": "Термодинамическая солнечная электростанция, в которой энергия солнечного излучения, поглощенная теплоносителем в первом контуре, передается через теплообменник теплоносителю второго контура.",
        "rightAnswer": "Двухконтурная солнечная электростанция",
        "wrongAnswers": [
            "Термодинамическая солнечная электростанция",
            "Фотоэлектрическая солнечная электростанция",
            "Башенная солнечная электростанция",
            "Модульная солнечная электростанция"
        ]
    },
    {
        "id": 39,
        "text": "Солнечная электростанция, состоящая из повторяющихся конструктивных элементов-модулей, содержащих однотипные концентраторы и приемники энергии солнечного излучения.",
        "rightAnswer": "Модульная солнечная электростанция",
        "wrongAnswers": [
            "Термодинамическая солнечная электростанция",
            "Фотоэлектрическая солнечная электростанция",
            "Башенная солнечная электростанция",
            "Двухконтурная солнечная электростанция"
        ]
    },
    {
        "id": 40,
        "text": "Приемник солнечного излучения, поглощающая поверхность которого находится в вакуумированном пространстве, ограниченном прозрачной оболочкой.",
        "rightAnswer": "Вакуумированный приемник",
        "wrongAnswers": [
            "Центральный приемник",
            "Полостной приемник солнечного излучения",
            "Солнечный парогенератор",
            "Солнечный экономайзер"
        ]
    },
    {
        "id": 41,
        "text": "Приемник солнечного излучения в башенной солнечной электростанции.",
        "rightAnswer": "Центральный приемник",
        "wrongAnswers": [
            "Вакуумированный приемник",
            "Полостной приемник солнечного излучения",
            "Солнечный парогенератор",
            "Солнечный экономайзер"
        ]
    },
    {
        "id": 42,
        "text": "Приемник солнечного излучения, тепловоспринимающая поверхность которого имеет форму полости различной конфигурации.",
        "rightAnswer": "Полостной приемник солнечного излучения",
        "wrongAnswers": [
            "Вакуумированный приемник",
            "Центральный приемник",
            "Солнечный парогенератор",
            "Солнечный экономайзер"
        ]
    },
    {
        "id": 43,
        "text": "Элемент термодинамических солнечных электростанций, в котором происходит генерация пара.",
        "rightAnswer": "Солнечный парогенератор",
        "wrongAnswers": [
            "Вакуумированный приемник",
            "Центральный приемник",
            "Полостной приемник солнечного излучения",
            "Солнечный экономайзер"
        ]
    },
    {
        "id": 44,
        "text": "Элемент термодинамических солнечных электростанций, в котором происходит предварительный нагрев теплоносителя перед его поступлением в солнечный парогенератор.",
        "rightAnswer": "Солнечный экономайзер",
        "wrongAnswers": [
            "Вакуумированный приемник",
            "Центральный приемник",
            "Полостной приемник солнечного излучения",
            "Солнечный парогенератор"
        ]
    }
]